Metadata-Version: 2.1
Name: vcenter-info
Version: 0.0.2
Summary: Simple view of vCenter data
Home-page: https://github.com/susrik/vcenter-info
Author: Erik Reid
Author-email: nobody@nowhere.org
License: UNKNOWN
Platform: UNKNOWN
Classifier: Programming Language :: Python :: 3
Classifier: Programming Language :: Python :: 3.6
Classifier: Programming Language :: Python :: 3.7
Classifier: Programming Language :: Python :: 3.8
Classifier: License :: OSI Approved :: MIT License
Classifier: Operating System :: OS Independent
Classifier: Development Status :: 4 - Beta
Requires-Python: >=3.5
